quackamollie/_bundle/__init__.py
quackamollie-0.1.dist-info/LICENSE
quackamollie-0.1.dist-info/METADATA
quackamollie-0.1.dist-info/WHEEL
quackamollie-0.1.dist-info/top_level.txt
quackamollie-0.1.dist-info/RECORD
