Metadata-Version: 2.1
Name: quackamollie
Version: 0.1
Summary: Run on your computer your own Telegram LLM chatbot using Ollama backed by models with Langchain or Llama-Index
Author-email: QuactorAI <quacktorai@gmail.com>
License: MIT License
Project-URL: Homepage, https://gitlab.com/forge_of_absurd_ducks/quackamollie/quackamollie
Keywords: telegram,bot,aiogram,langchain,llama-index,ollama,llmsherpa
Classifier: License :: OSI Approved :: MIT License
Classifier: Programming Language :: Python
Classifier: Programming Language :: Python :: 3 :: Only
Classifier: Programming Language :: Python :: 3.10
Requires-Python: >=3.10
License-File: LICENSE
Requires-Dist: quackamollie-core>=0.1
Provides-Extra: all
Requires-Dist: quackamollie-ollama-model-manager; extra == "all"
Requires-Dist: quackamollie-langchain-model-manager; extra == "all"
Requires-Dist: quackamollie-model-langchain-simple; extra == "all"
Requires-Dist: quackamollie-llama-index-model-manager; extra == "all"
Requires-Dist: quackamollie-model-llama-index-simple; extra == "all"
Provides-Extra: common
Requires-Dist: quackamollie-ollama-model-manager; extra == "common"
Requires-Dist: quackamollie-langchain-model-manager; extra == "common"
Requires-Dist: quackamollie-model-langchain-simple; extra == "common"
Requires-Dist: quackamollie-llama-index-model-manager; extra == "common"
Requires-Dist: quackamollie-model-llama-index-simple; extra == "common"
Provides-Extra: devtools
Requires-Dist: pgcli; extra == "devtools"
Requires-Dist: quackamollie-devtools; extra == "devtools"
Provides-Extra: langchain
Requires-Dist: quackamollie-langchain-model-manager; extra == "langchain"
Provides-Extra: langchain-all
Requires-Dist: quackamollie-langchain-model-manager; extra == "langchain-all"
Requires-Dist: quackamollie-model-langchain-simple; extra == "langchain-all"
Provides-Extra: langchain-common
Requires-Dist: quackamollie-langchain-model-manager; extra == "langchain-common"
Requires-Dist: quackamollie-model-langchain-simple; extra == "langchain-common"
Provides-Extra: lint
Requires-Dist: check-manifest; extra == "lint"
Requires-Dist: flake8; extra == "lint"
Requires-Dist: readme-renderer; extra == "lint"
Requires-Dist: safety; extra == "lint"
Requires-Dist: setuptools; extra == "lint"
Requires-Dist: twine; extra == "lint"
Requires-Dist: wheel; extra == "lint"
Provides-Extra: llama-index
Requires-Dist: quackamollie-llama-index-model-manager; extra == "llama-index"
Provides-Extra: llama-index-all
Requires-Dist: quackamollie-llama-index-model-manager; extra == "llama-index-all"
Requires-Dist: quackamollie-model-llama-index-simple; extra == "llama-index-all"
Provides-Extra: llama-index-common
Requires-Dist: quackamollie-llama-index-model-manager; extra == "llama-index-common"
Requires-Dist: quackamollie-model-llama-index-simple; extra == "llama-index-common"
Provides-Extra: ollama
Requires-Dist: quackamollie-ollama-model-manager; extra == "ollama"
Provides-Extra: test
Requires-Dist: coverage; extra == "test"
Requires-Dist: pytest; extra == "test"
Requires-Dist: pytest-cov; extra == "test"
Requires-Dist: pytest-xdist; extra == "test"
Requires-Dist: tox; extra == "test"
